README.rst
setup.py
PackageMega.egg-info/PKG-INFO
PackageMega.egg-info/SOURCES.txt
PackageMega.egg-info/dependency_links.txt
PackageMega.egg-info/entry_points.txt
PackageMega.egg-info/requires.txt
PackageMega.egg-info/top_level.txt
packagemega/__init__.py
packagemega/base_recipe.py
packagemega/constructed_file.py
packagemega/custom_errors.py
packagemega/mini_language.py
packagemega/repo.py
packagemega/source_file.py
packagemega/version.py
packagemega/cli/__init__.py
packagemega/cli/cli.py