Metadata-Version: 1.1
Name: PackageMega
Version: 0.1.3
Summary: Simple package manager to download and keep track of biological databases.
Home-page: https://github.com/dcdanko/PackageMega
Author: David C Danko
Author-email: dcd3001@med.cornell.edu
License: UNKNOWN
Platform: UNKNOWN
Classifier: Development Status :: 2 - Pre-Alpha
Classifier: Programming Language :: Python
Classifier: Programming Language :: Python :: 3
